debug_adapter/__init__.py
debug_adapter/__main__.py
debug_adapter/base_schema.py
debug_adapter/cli.py
debug_adapter/command_processor.py
debug_adapter/debug_adapter.py
debug_adapter/internal_classes.py
debug_adapter/log.py
debug_adapter/schema.py
debug_adapter/threads.py
debug_adapter/tools.py
tests/__init__.py
tests/conftest.py
tests/environment.py
tests/helpers.py
tests/pytest_fixtures.py
tests/requirements.txt
tests/standard_requests.py
tests/t_session.py
tests/test_arguments.py
tests/test_basic.py
tests/test_debug_actions.py
tests/test_patterns.py
tests/test_timeline.py
tests/timeline.md
tests/timeline.py
tests/patterns/__init__.py
tests/patterns/_impl.py
tests/patterns/dap.py
tests/patterns/some.py
tests/target/blink.elf
tests/target/build_all.py
tests/target/coredump.elf
tests/target/host/test_app.c
tests/target/host/test_app_src2.c
cx_debug_adapter-1.0.0.dist-info/LICENSE
cx_debug_adapter-1.0.0.dist-info/METADATA
cx_debug_adapter-1.0.0.dist-info/WHEEL
cx_debug_adapter-1.0.0.dist-info/top_level.txt
cx_debug_adapter-1.0.0.dist-info/RECORD
