Metadata-Version: 2.1
Name: cx-debug-adapter
Version: 1.0.0
Summary: C & CPP debugger adapter for Python
License: Apache License 2.0
Platform: any
License-File: LICENSE
Requires-Dist: setuptools (>=21)
Requires-Dist: click
Requires-Dist: esp-debug-backend
Requires-Dist: requests (>=2.21.0)
